{
  "udp": {
    "60": {
      "start": {
        "connected": [
          {
            "socket": 5,
            "local_host": "172.17.0.2",
            "local_port": 38063,
            "remote_host": "172.20.25.101",
            "remote_port": 32201
          }
        ],
        "version": "iperf 3.12",
        "system_info": "Linux a7c783a6ceaf 6.8.0-87-generic #88~22.04.1-Ubuntu SMP PREEMPT_DYNAMIC Tue Oct 14 14:03:14 UTC 2 x86_64",
        "timestamp": {
          "time": "Mon, 01 Dec 2025 06:32:43 GMT",
          "timesecs": 1764570763
        },
        "connecting_to": {
          "host": "api-int.tenoran.automation.otic.open6g.net",
          "port": 32201
        },
        "cookie": "t2zrpxxvf6kbtueewbxcsiqgyotzh7jk5e2i",
        "target_bitrate": 60000000,
        "sock_bufsize": 0,
        "sndbuf_actual": 212992,
        "rcvbuf_actual": 212992,
        "test_start": {
          "protocol": "UDP",
          "num_streams": 1,
          "blksize": 1348,
          "omit": 0,
          "duration": 10,
          "bytes": 0,
          "blocks": 0,
          "reverse": 1,
          "tos": 0,
          "target_bitrate": 60000000
        }
      },
      "intervals": [
        {
          "streams": [
            {
              "socket": 5,
              "start": 0,
              "end": 1.000209,
              "seconds": 1.0002089738845825,
              "bytes": 7440960,
              "bits_per_second": 59515242.8685059,
              "jitter_ms": 0.18934866035258494,
              "lost_packets": 17,
              "packets": 5537,
              "lost_percent": 0.307025465053278,
              "omitted": false,
              "sender": false
            }
          ],
          "sum": {
            "start": 0,
            "end": 1.000209,
            "seconds": 1.0002089738845825,
            "bytes": 7440960,
            "bits_per_second": 59515242.8685059,
            "jitter_ms": 0.18934866035258494,
            "lost_packets": 17,
            "packets": 5537,
            "lost_percent": 0.307025465053278,
            "omitted": false,
            "sender": false
          }
        },
        {
          "streams": [
            {
              "socket": 5,
              "start": 1.000209,
              "end": 2.000206,
              "seconds": 0.9999970197677612,
              "bytes": 7500272,
              "bits_per_second": 60002354.82095224,
              "jitter_ms": 0.18002503180347865,
              "lost_packets": 0,
              "packets": 5564,
              "lost_percent": 0,
              "omitted": false,
              "sender": false
            }
          ],
          "sum": {
            "start": 1.000209,
            "end": 2.000206,
            "seconds": 0.9999970197677612,
            "bytes": 7500272,
            "bits_per_second": 60002354.82095224,
            "jitter_ms": 0.18002503180347865,
            "lost_packets": 0,
            "packets": 5564,
            "lost_percent": 0,
            "omitted": false,
            "sender": false
          }
        },
        {
          "streams": [
            {
              "socket": 5,
              "start": 2.000206,
              "end": 3.000206,
              "seconds": 1,
              "bytes": 7498924,
              "bits_per_second": 59991392,
              "jitter_ms": 0.20002223147847634,
              "lost_packets": 0,
              "packets": 5563,
              "lost_percent": 0,
              "omitted": false,
              "sender": false
            }
          ],
          "sum": {
            "start": 2.000206,
            "end": 3.000206,
            "seconds": 1,
            "bytes": 7498924,
            "bits_per_second": 59991392,
            "jitter_ms": 0.20002223147847634,
            "lost_packets": 0,
            "packets": 5563,
            "lost_percent": 0,
            "omitted": false,
            "sender": false
          }
        },
        {
          "streams": [
            {
              "socket": 5,
              "start": 3.000206,
              "end": 4.000215,
              "seconds": 1.0000089406967163,
              "bytes": 7416696,
              "bits_per_second": 59333037.52130626,
              "jitter_ms": 0.20989298226341768,
              "lost_packets": 0,
              "packets": 5502,
              "lost_percent": 0,
              "omitted": false,
              "sender": false
            }
          ],
          "sum": {
            "start": 3.000206,
            "end": 4.000215,
            "seconds": 1.0000089406967163,
            "bytes": 7416696,
            "bits_per_second": 59333037.52130626,
            "jitter_ms": 0.20989298226341768,
            "lost_packets": 0,
            "packets": 5502,
            "lost_percent": 0,
            "omitted": false,
            "sender": false
          }
        },
        {
          "streams": [
            {
              "socket": 5,
              "start": 4.000215,
              "end": 5.000206,
              "seconds": 0.999990999698639,
              "bytes": 7583848,
              "bits_per_second": 60671330.06025452,
              "jitter_ms": 0.19109253440718882,
              "lost_packets": 0,
              "packets": 5626,
              "lost_percent": 0,
              "omitted": false,
              "sender": false
            }
          ],
          "sum": {
            "start": 4.000215,
            "end": 5.000206,
            "seconds": 0.999990999698639,
            "bytes": 7583848,
            "bits_per_second": 60671330.06025452,
            "jitter_ms": 0.19109253440718882,
            "lost_packets": 0,
            "packets": 5626,
            "lost_percent": 0,
            "omitted": false,
            "sender": false
          }
        },
        {
          "streams": [
            {
              "socket": 5,
              "start": 5.000206,
              "end": 6.000216,
              "seconds": 1.0000100135803223,
              "bytes": 7500272,
              "bits_per_second": 60001575.16940758,
              "jitter_ms": 0.16012974928353246,
              "lost_packets": 0,
              "packets": 5564,
              "lost_percent": 0,
              "omitted": false,
              "sender": false
            }
          ],
          "sum": {
            "start": 5.000206,
            "end": 6.000216,
            "seconds": 1.0000100135803223,
            "bytes": 7500272,
            "bits_per_second": 60001575.16940758,
            "jitter_ms": 0.16012974928353246,
            "lost_packets": 0,
            "packets": 5564,
            "lost_percent": 0,
            "omitted": false,
            "sender": false
          }
        },
        {
          "streams": [
            {
              "socket": 5,
              "start": 6.000216,
              "end": 7.000192,
              "seconds": 0.9999759793281555,
              "bytes": 7500272,
              "bits_per_second": 60003617.3272013,
              "jitter_ms": 0.23932915013990627,
              "lost_packets": 0,
              "packets": 5564,
              "lost_percent": 0,
              "omitted": false,
              "sender": false
            }
          ],
          "sum": {
            "start": 6.000216,
            "end": 7.000192,
            "seconds": 0.9999759793281555,
            "bytes": 7500272,
            "bits_per_second": 60003617.3272013,
            "jitter_ms": 0.23932915013990627,
            "lost_packets": 0,
            "packets": 5564,
            "lost_percent": 0,
            "omitted": false,
            "sender": false
          }
        },
        {
          "streams": [
            {
              "socket": 5,
              "start": 7.000192,
              "end": 8.000204,
              "seconds": 1.0000120401382446,
              "bytes": 7498924,
              "bits_per_second": 59990669.70404337,
              "jitter_ms": 0.19668622559168158,
              "lost_packets": 0,
              "packets": 5563,
              "lost_percent": 0,
              "omitted": false,
              "sender": false
            }
          ],
          "sum": {
            "start": 7.000192,
            "end": 8.000204,
            "seconds": 1.0000120401382446,
            "bytes": 7498924,
            "bits_per_second": 59990669.70404337,
            "jitter_ms": 0.19668622559168158,
            "lost_packets": 0,
            "packets": 5563,
            "lost_percent": 0,
            "omitted": false,
            "sender": false
          }
        },
        {
          "streams": [
            {
              "socket": 5,
              "start": 8.000204,
              "end": 9.000164,
              "seconds": 0.9999600052833557,
              "bytes": 7500272,
              "bits_per_second": 60004575.86600912,
              "jitter_ms": 0.232928173782365,
              "lost_packets": 0,
              "packets": 5564,
              "lost_percent": 0,
              "omitted": false,
              "sender": false
            }
          ],
          "sum": {
            "start": 8.000204,
            "end": 9.000164,
            "seconds": 0.9999600052833557,
            "bytes": 7500272,
            "bits_per_second": 60004575.86600912,
            "jitter_ms": 0.232928173782365,
            "lost_packets": 0,
            "packets": 5564,
            "lost_percent": 0,
            "omitted": false,
            "sender": false
          }
        },
        {
          "streams": [
            {
              "socket": 5,
              "start": 9.000164,
              "end": 10.000225,
              "seconds": 1.00006103515625,
              "bytes": 7500272,
              "bits_per_second": 59998513.98132438,
              "jitter_ms": 0.19063557144329132,
              "lost_packets": 0,
              "packets": 5564,
              "lost_percent": 0,
              "omitted": false,
              "sender": false
            }
          ],
          "sum": {
            "start": 9.000164,
            "end": 10.000225,
            "seconds": 1.00006103515625,
            "bytes": 7500272,
            "bits_per_second": 59998513.98132438,
            "jitter_ms": 0.19063557144329132,
            "lost_packets": 0,
            "packets": 5564,
            "lost_percent": 0,
            "omitted": false,
            "sender": false
          }
        }
      ],
      "end": {
        "streams": [
          {
            "udp": {
              "socket": 5,
              "start": 0,
              "end": 10.011162,
              "seconds": 10.011162,
              "bytes": 75083600,
              "bits_per_second": 59999908.1025759,
              "jitter_ms": 0.19063557144329132,
              "lost_packets": 17,
              "packets": 55700,
              "lost_percent": 0.03052064631956912,
              "out_of_order": 0,
              "sender": false
            }
          }
        ],
        "sum": {
          "start": 0,
          "end": 10.000225,
          "seconds": 10.000225,
          "bytes": 75083600,
          "bits_per_second": 59999908.1025759,
          "jitter_ms": 0.19063557144329132,
          "lost_packets": 17,
          "packets": 55700,
          "lost_percent": 0.03052064631956912,
          "sender": false
        },
        "sum_sent": {
          "start": 0,
          "end": 10.011162,
          "seconds": 10.011162,
          "bytes": 75083600,
          "bits_per_second": 59999908.1025759,
          "jitter_ms": 0,
          "lost_packets": 0,
          "packets": 55700,
          "lost_percent": 0,
          "sender": true
        },
        "sum_received": {
          "start": 0,
          "end": 10.000225,
          "seconds": 10.000225,
          "bytes": 74940712,
          "bits_per_second": 59951220.6975343,
          "jitter_ms": 0.19063557144329132,
          "lost_packets": 17,
          "packets": 55611,
          "lost_percent": 0.03052064631956912,
          "sender": false
        },
        "cpu_utilization_percent": {
          "host_total": 8.496720523364,
          "host_user": 2.7142323767592416,
          "host_system": 5.782517975847262,
          "remote_total": 1.6515527382622537,
          "remote_user": 0.16922072661727858,
          "remote_system": 1.482332011644975
        }
      }
    }
  }
}