{
  "udp": {
    "30": {
      "start": {
        "connected": [
          {
            "socket": 10,
            "local_host": "172.17.0.2",
            "local_port": 55293,
            "remote_host": "10.100.1.101",
            "remote_port": 32201
          }
        ],
        "version": "iperf 3.12",
        "system_info": "Linux d35518d1e543 6.5.0-27-generic #28~22.04.1-Ubuntu SMP PREEMPT_DYNAMIC Fri Mar 15 10:51:06 UTC 2 x86_64",
        "timestamp": {
          "time": "Wed, 10 Jul 2024 04:01:42 GMT",
          "timesecs": 1720584102
        },
        "connecting_to": {
          "host": "api-int.edge.open5g.info",
          "port": 32201
        },
        "cookie": "ce4ek5p4ww4xyi3fbgaoilpqaz73keekllf6",
        "target_bitrate": 30000000,
        "sock_bufsize": 0,
        "sndbuf_actual": 212992,
        "rcvbuf_actual": 212992,
        "test_start": {
          "protocol": "UDP",
          "num_streams": 1,
          "blksize": 1398,
          "omit": 0,
          "duration": 10,
          "bytes": 0,
          "blocks": 0,
          "reverse": 1,
          "tos": 0,
          "target_bitrate": 30000000
        }
      },
      "intervals": [
        {
          "streams": [
            {
              "socket": 10,
              "start": 0,
              "end": 1.000271,
              "seconds": 1.000270962715149,
              "bytes": 3755028,
              "bits_per_second": 30032086.42432088,
              "jitter_ms": 0.00996022606237966,
              "lost_packets": 0,
              "packets": 2686,
              "lost_percent": 0,
              "omitted": false,
              "sender": false
            }
          ],
          "sum": {
            "start": 0,
            "end": 1.000271,
            "seconds": 1.000270962715149,
            "bytes": 3755028,
            "bits_per_second": 30032086.42432088,
            "jitter_ms": 0.00996022606237966,
            "lost_packets": 0,
            "packets": 2686,
            "lost_percent": 0,
            "omitted": false,
            "sender": false
          }
        },
        {
          "streams": [
            {
              "socket": 10,
              "start": 1.000271,
              "end": 2.000278,
              "seconds": 1.0000070333480835,
              "bytes": 3750834,
              "bits_per_second": 30006460.954115357,
              "jitter_ms": 0.03411856733508403,
              "lost_packets": 0,
              "packets": 2683,
              "lost_percent": 0,
              "omitted": false,
              "sender": false
            }
          ],
          "sum": {
            "start": 1.000271,
            "end": 2.000278,
            "seconds": 1.0000070333480835,
            "bytes": 3750834,
            "bits_per_second": 30006460.954115357,
            "jitter_ms": 0.03411856733508403,
            "lost_packets": 0,
            "packets": 2683,
            "lost_percent": 0,
            "omitted": false,
            "sender": false
          }
        },
        {
          "streams": [
            {
              "socket": 10,
              "start": 2.000278,
              "end": 3.00016,
              "seconds": 0.9998819828033447,
              "bytes": 3749436,
              "bits_per_second": 29999028.4012343,
              "jitter_ms": 0.08988887184534805,
              "lost_packets": 0,
              "packets": 2682,
              "lost_percent": 0,
              "omitted": false,
              "sender": false
            }
          ],
          "sum": {
            "start": 2.000278,
            "end": 3.00016,
            "seconds": 0.9998819828033447,
            "bytes": 3749436,
            "bits_per_second": 29999028.4012343,
            "jitter_ms": 0.08988887184534805,
            "lost_packets": 0,
            "packets": 2682,
            "lost_percent": 0,
            "omitted": false,
            "sender": false
          }
        },
        {
          "streams": [
            {
              "socket": 10,
              "start": 3.00016,
              "end": 4.000273,
              "seconds": 1.0001130104064941,
              "bytes": 3725670,
              "bits_per_second": 29801992.064762425,
              "jitter_ms": 0.017191430686215908,
              "lost_packets": 18,
              "packets": 2683,
              "lost_percent": 0.6708907938874394,
              "omitted": false,
              "sender": false
            }
          ],
          "sum": {
            "start": 3.00016,
            "end": 4.000273,
            "seconds": 1.0001130104064941,
            "bytes": 3725670,
            "bits_per_second": 29801992.064762425,
            "jitter_ms": 0.017191430686215908,
            "lost_packets": 18,
            "packets": 2683,
            "lost_percent": 0.6708907938874394,
            "omitted": false,
            "sender": false
          }
        },
        {
          "streams": [
            {
              "socket": 10,
              "start": 4.000273,
              "end": 5.000274,
              "seconds": 1.0000009536743164,
              "bytes": 3749436,
              "bits_per_second": 29995459.394100767,
              "jitter_ms": 0.09566746629245718,
              "lost_packets": 0,
              "packets": 2682,
              "lost_percent": 0,
              "omitted": false,
              "sender": false
            }
          ],
          "sum": {
            "start": 4.000273,
            "end": 5.000274,
            "seconds": 1.0000009536743164,
            "bytes": 3749436,
            "bits_per_second": 29995459.394100767,
            "jitter_ms": 0.09566746629245718,
            "lost_packets": 0,
            "packets": 2682,
            "lost_percent": 0,
            "omitted": false,
            "sender": false
          }
        },
        {
          "streams": [
            {
              "socket": 10,
              "start": 5.000274,
              "end": 6.000274,
              "seconds": 1,
              "bytes": 3749436,
              "bits_per_second": 29995488,
              "jitter_ms": 0.021046059087646042,
              "lost_packets": 0,
              "packets": 2682,
              "lost_percent": 0,
              "omitted": false,
              "sender": false
            }
          ],
          "sum": {
            "start": 5.000274,
            "end": 6.000274,
            "seconds": 1,
            "bytes": 3749436,
            "bits_per_second": 29995488,
            "jitter_ms": 0.021046059087646042,
            "lost_packets": 0,
            "packets": 2682,
            "lost_percent": 0,
            "omitted": false,
            "sender": false
          }
        },
        {
          "streams": [
            {
              "socket": 10,
              "start": 6.000274,
              "end": 7.000239,
              "seconds": 0.999965012073517,
              "bytes": 3606840,
              "bits_per_second": 28855729.602145936,
              "jitter_ms": 0.045566122826129915,
              "lost_packets": 0,
              "packets": 2580,
              "lost_percent": 0,
              "omitted": false,
              "sender": false
            }
          ],
          "sum": {
            "start": 6.000274,
            "end": 7.000239,
            "seconds": 0.999965012073517,
            "bytes": 3606840,
            "bits_per_second": 28855729.602145936,
            "jitter_ms": 0.045566122826129915,
            "lost_packets": 0,
            "packets": 2580,
            "lost_percent": 0,
            "omitted": false,
            "sender": false
          }
        },
        {
          "streams": [
            {
              "socket": 10,
              "start": 7.000239,
              "end": 8.000021,
              "seconds": 0.9997820258140564,
              "bytes": 3875256,
              "bits_per_second": 31008807.119488955,
              "jitter_ms": 0.13266635024695564,
              "lost_packets": 0,
              "packets": 2772,
              "lost_percent": 0,
              "omitted": false,
              "sender": false
            }
          ],
          "sum": {
            "start": 7.000239,
            "end": 8.000021,
            "seconds": 0.9997820258140564,
            "bytes": 3875256,
            "bits_per_second": 31008807.119488955,
            "jitter_ms": 0.13266635024695564,
            "lost_packets": 0,
            "packets": 2772,
            "lost_percent": 0,
            "omitted": false,
            "sender": false
          }
        },
        {
          "streams": [
            {
              "socket": 10,
              "start": 8.000021,
              "end": 9.000178,
              "seconds": 1.0001569986343384,
              "bytes": 3611034,
              "bits_per_second": 28883737.29269046,
              "jitter_ms": 0.7808497195287013,
              "lost_packets": 6,
              "packets": 2589,
              "lost_percent": 0.23174971031286212,
              "omitted": false,
              "sender": false
            }
          ],
          "sum": {
            "start": 8.000021,
            "end": 9.000178,
            "seconds": 1.0001569986343384,
            "bytes": 3611034,
            "bits_per_second": 28883737.29269046,
            "jitter_ms": 0.7808497195287013,
            "lost_packets": 6,
            "packets": 2589,
            "lost_percent": 0.23174971031286212,
            "omitted": false,
            "sender": false
          }
        },
        {
          "streams": [
            {
              "socket": 10,
              "start": 9.000178,
              "end": 10.000178,
              "seconds": 1,
              "bytes": 3900420,
              "bits_per_second": 31203360,
              "jitter_ms": 0.0383107534979381,
              "lost_packets": 0,
              "packets": 2790,
              "lost_percent": 0,
              "omitted": false,
              "sender": false
            }
          ],
          "sum": {
            "start": 9.000178,
            "end": 10.000178,
            "seconds": 1,
            "bytes": 3900420,
            "bits_per_second": 31203360,
            "jitter_ms": 0.0383107534979381,
            "lost_packets": 0,
            "packets": 2790,
            "lost_percent": 0,
            "omitted": false,
            "sender": false
          }
        }
      ],
      "end": {
        "streams": [
          {
            "udp": {
              "socket": 10,
              "start": 0,
              "end": 10.000178,
              "seconds": 10.000178,
              "bytes": 37506942,
              "bits_per_second": 30005019.51065271,
              "jitter_ms": 0.0383107534979381,
              "lost_packets": 24,
              "packets": 26829,
              "lost_percent": 0.08945544000894555,
              "out_of_order": 0,
              "sender": false
            }
          }
        ],
        "sum": {
          "start": 0,
          "end": 10.000178,
          "seconds": 10.000178,
          "bytes": 37506942,
          "bits_per_second": 30005019.51065271,
          "jitter_ms": 0.0383107534979381,
          "lost_packets": 24,
          "packets": 26829,
          "lost_percent": 0.08945544000894555,
          "sender": false
        },
        "sum_sent": {
          "start": 0,
          "end": 10.000178,
          "seconds": 10.000178,
          "bytes": 37506942,
          "bits_per_second": 30005019.51065271,
          "jitter_ms": 0,
          "lost_packets": 0,
          "packets": 26829,
          "lost_percent": 0,
          "sender": true
        },
        "sum_received": {
          "start": 0,
          "end": 10.000178,
          "seconds": 10.000178,
          "bytes": 37473390,
          "bits_per_second": 29978178.388424687,
          "jitter_ms": 0.0383107534979381,
          "lost_packets": 24,
          "packets": 26829,
          "lost_percent": 0.08945544000894555,
          "sender": false
        },
        "cpu_utilization_percent": {
          "host_total": 3.5948226133532093,
          "host_user": 1.0756784937646566,
          "host_system": 2.5190846504104365,
          "remote_total": 0.209973,
          "remote_user": 0.012502,
          "remote_system": 0.197474
        }
      }
    }
  }
}