{
  "udp": {
    "20": {
      "start": {
        "connected": [
          {
            "socket": 10,
            "local_host": "172.17.0.2",
            "local_port": 45392,
            "remote_host": "172.20.25.101",
            "remote_port": 32201
          }
        ],
        "version": "iperf 3.12",
        "system_info": "Linux d4d68b2d0349 6.8.0-60-generic #63~22.04.1-Ubuntu SMP PREEMPT_DYNAMIC Tue Apr 22 19:00:15 UTC 2 x86_64",
        "timestamp": {
          "time": "Fri, 04 Jul 2025 05:01:24 GMT",
          "timesecs": 1751605284
        },
        "connecting_to": {
          "host": "api-int.tenoran.automation.otic.open6g.net",
          "port": 32201
        },
        "cookie": "b62xj5ysh3jgawf44b726xhsnr4qvucjrmtc",
        "target_bitrate": 20000000,
        "sock_bufsize": 0,
        "sndbuf_actual": 212992,
        "rcvbuf_actual": 212992,
        "test_start": {
          "protocol": "UDP",
          "num_streams": 1,
          "blksize": 1348,
          "omit": 0,
          "duration": 10,
          "bytes": 0,
          "blocks": 0,
          "reverse": 1,
          "tos": 0,
          "target_bitrate": 20000000
        }
      },
      "intervals": [
        {
          "streams": [
            {
              "socket": 10,
              "start": 0,
              "end": 1.000234,
              "seconds": 1.0002340078353882,
              "bytes": 2437184,
              "bits_per_second": 19492910.506207027,
              "jitter_ms": 0.32416063216185426,
              "lost_packets": 0,
              "packets": 1808,
              "lost_percent": 0,
              "omitted": false,
              "sender": false
            }
          ],
          "sum": {
            "start": 0,
            "end": 1.000234,
            "seconds": 1.0002340078353882,
            "bytes": 2437184,
            "bits_per_second": 19492910.506207027,
            "jitter_ms": 0.32416063216185426,
            "lost_packets": 0,
            "packets": 1808,
            "lost_percent": 0,
            "omitted": false,
            "sender": false
          }
        },
        {
          "streams": [
            {
              "socket": 10,
              "start": 1.000234,
              "end": 2.000121,
              "seconds": 0.999886989593506,
              "bytes": 2507280,
              "bits_per_second": 20060507.046055753,
              "jitter_ms": 0.3650923895485592,
              "lost_packets": 0,
              "packets": 1860,
              "lost_percent": 0,
              "omitted": false,
              "sender": false
            }
          ],
          "sum": {
            "start": 1.000234,
            "end": 2.000121,
            "seconds": 0.999886989593506,
            "bytes": 2507280,
            "bits_per_second": 20060507.046055753,
            "jitter_ms": 0.3650923895485592,
            "lost_packets": 0,
            "packets": 1860,
            "lost_percent": 0,
            "omitted": false,
            "sender": false
          }
        },
        {
          "streams": [
            {
              "socket": 10,
              "start": 2.000121,
              "end": 3.000082,
              "seconds": 0.999961018562317,
              "bytes": 2539632,
              "bits_per_second": 20317848.0189264,
              "jitter_ms": 0.14270522063758012,
              "lost_packets": 0,
              "packets": 1884,
              "lost_percent": 0,
              "omitted": false,
              "sender": false
            }
          ],
          "sum": {
            "start": 2.000121,
            "end": 3.000082,
            "seconds": 0.999961018562317,
            "bytes": 2539632,
            "bits_per_second": 20317848.0189264,
            "jitter_ms": 0.14270522063758012,
            "lost_packets": 0,
            "packets": 1884,
            "lost_percent": 0,
            "omitted": false,
            "sender": false
          }
        },
        {
          "streams": [
            {
              "socket": 10,
              "start": 3.000082,
              "end": 4.000231,
              "seconds": 1.0001490116119385,
              "bytes": 2456056,
              "bits_per_second": 19645520.589309618,
              "jitter_ms": 0.3141862448527382,
              "lost_packets": 0,
              "packets": 1822,
              "lost_percent": 0,
              "omitted": false,
              "sender": false
            }
          ],
          "sum": {
            "start": 3.000082,
            "end": 4.000231,
            "seconds": 1.0001490116119385,
            "bytes": 2456056,
            "bits_per_second": 19645520.589309618,
            "jitter_ms": 0.3141862448527382,
            "lost_packets": 0,
            "packets": 1822,
            "lost_percent": 0,
            "omitted": false,
            "sender": false
          }
        },
        {
          "streams": [
            {
              "socket": 10,
              "start": 4.000231,
              "end": 5.000216,
              "seconds": 0.9999849796295166,
              "bytes": 2480320,
              "bits_per_second": 19842858.047079317,
              "jitter_ms": 0.10380768751895637,
              "lost_packets": 0,
              "packets": 1840,
              "lost_percent": 0,
              "omitted": false,
              "sender": false
            }
          ],
          "sum": {
            "start": 4.000231,
            "end": 5.000216,
            "seconds": 0.9999849796295166,
            "bytes": 2480320,
            "bits_per_second": 19842858.047079317,
            "jitter_ms": 0.10380768751895637,
            "lost_packets": 0,
            "packets": 1840,
            "lost_percent": 0,
            "omitted": false,
            "sender": false
          }
        },
        {
          "streams": [
            {
              "socket": 10,
              "start": 5.000216,
              "end": 6.000223,
              "seconds": 1.0000070333480835,
              "bytes": 2523456,
              "bits_per_second": 20187506.014243264,
              "jitter_ms": 0.3207975650935173,
              "lost_packets": 0,
              "packets": 1872,
              "lost_percent": 0,
              "omitted": false,
              "sender": false
            }
          ],
          "sum": {
            "start": 5.000216,
            "end": 6.000223,
            "seconds": 1.0000070333480835,
            "bytes": 2523456,
            "bits_per_second": 20187506.014243264,
            "jitter_ms": 0.3207975650935173,
            "lost_packets": 0,
            "packets": 1872,
            "lost_percent": 0,
            "omitted": false,
            "sender": false
          }
        },
        {
          "streams": [
            {
              "socket": 10,
              "start": 6.000223,
              "end": 7.000082,
              "seconds": 0.9998589754104614,
              "bytes": 2531544,
              "bits_per_second": 20255208.482462257,
              "jitter_ms": 0.14919977838852427,
              "lost_packets": 0,
              "packets": 1878,
              "lost_percent": 0,
              "omitted": false,
              "sender": false
            }
          ],
          "sum": {
            "start": 6.000223,
            "end": 7.000082,
            "seconds": 0.9998589754104614,
            "bytes": 2531544,
            "bits_per_second": 20255208.482462257,
            "jitter_ms": 0.14919977838852427,
            "lost_packets": 0,
            "packets": 1878,
            "lost_percent": 0,
            "omitted": false,
            "sender": false
          }
        },
        {
          "streams": [
            {
              "socket": 10,
              "start": 7.000082,
              "end": 8.000227,
              "seconds": 1.0001449584960938,
              "bytes": 2516716,
              "bits_per_second": 20130809.868076373,
              "jitter_ms": 0.062265303333610224,
              "lost_packets": 0,
              "packets": 1867,
              "lost_percent": 0,
              "omitted": false,
              "sender": false
            }
          ],
          "sum": {
            "start": 7.000082,
            "end": 8.000227,
            "seconds": 1.0001449584960938,
            "bytes": 2516716,
            "bits_per_second": 20130809.868076373,
            "jitter_ms": 0.062265303333610224,
            "lost_packets": 0,
            "packets": 1867,
            "lost_percent": 0,
            "omitted": false,
            "sender": false
          }
        },
        {
          "streams": [
            {
              "socket": 10,
              "start": 8.000227,
              "end": 9.000214,
              "seconds": 0.999987006187439,
              "bytes": 2433140,
              "bits_per_second": 19465372.929407276,
              "jitter_ms": 0.12308154648447785,
              "lost_packets": 0,
              "packets": 1805,
              "lost_percent": 0,
              "omitted": false,
              "sender": false
            }
          ],
          "sum": {
            "start": 8.000227,
            "end": 9.000214,
            "seconds": 0.999987006187439,
            "bytes": 2433140,
            "bits_per_second": 19465372.929407276,
            "jitter_ms": 0.12308154648447785,
            "lost_packets": 0,
            "packets": 1805,
            "lost_percent": 0,
            "omitted": false,
            "sender": false
          }
        },
        {
          "streams": [
            {
              "socket": 10,
              "start": 9.000214,
              "end": 10.000247,
              "seconds": 1.0000330209732056,
              "bytes": 2519412,
              "bits_per_second": 20154630.474487133,
              "jitter_ms": 0.31962864170880156,
              "lost_packets": 0,
              "packets": 1869,
              "lost_percent": 0,
              "omitted": false,
              "sender": false
            }
          ],
          "sum": {
            "start": 9.000214,
            "end": 10.000247,
            "seconds": 1.0000330209732056,
            "bytes": 2519412,
            "bits_per_second": 20154630.474487133,
            "jitter_ms": 0.31962864170880156,
            "lost_packets": 0,
            "packets": 1869,
            "lost_percent": 0,
            "omitted": false,
            "sender": false
          }
        }
      ],
      "end": {
        "streams": [
          {
            "udp": {
              "socket": 10,
              "start": 0,
              "end": 10.000247,
              "seconds": 10.000247,
              "bytes": 25002704,
              "bits_per_second": 20001669.15877178,
              "jitter_ms": 0.31962864170880156,
              "lost_packets": 0,
              "packets": 18505,
              "lost_percent": 0,
              "out_of_order": 0,
              "sender": false
            }
          }
        ],
        "sum": {
          "start": 0,
          "end": 10.000247,
          "seconds": 10.000247,
          "bytes": 25002704,
          "bits_per_second": 20001669.15877178,
          "jitter_ms": 0.31962864170880156,
          "lost_packets": 0,
          "packets": 18505,
          "lost_percent": 0,
          "sender": false
        },
        "sum_sent": {
          "start": 0,
          "end": 10.000247,
          "seconds": 10.000247,
          "bytes": 25002704,
          "bits_per_second": 20001669.15877178,
          "jitter_ms": 0,
          "lost_packets": 0,
          "packets": 18505,
          "lost_percent": 0,
          "sender": true
        },
        "sum_received": {
          "start": 0,
          "end": 10.000247,
          "seconds": 10.000247,
          "bytes": 24944740,
          "bits_per_second": 19955299.10411213,
          "jitter_ms": 0.31962864170880156,
          "lost_packets": 0,
          "packets": 18505,
          "lost_percent": 0,
          "sender": false
        },
        "cpu_utilization_percent": {
          "host_total": 3.528946027686196,
          "host_user": 0.995594153428526,
          "host_system": 2.5333914916173628,
          "remote_total": 0.39173,
          "remote_user": 0.024049,
          "remote_system": 0.367681
        }
      }
    }
  }
}