{
  "udp": {
    "70": {
      "start": {
        "connected": [
          {
            "socket": 5,
            "local_host": "172.17.0.2",
            "local_port": 35195,
            "remote_host": "172.20.25.101",
            "remote_port": 32201
          }
        ],
        "version": "iperf 3.12",
        "system_info": "Linux 3356230628a3 6.8.0-87-generic #88~22.04.1-Ubuntu SMP PREEMPT_DYNAMIC Tue Oct 14 14:03:14 UTC 2 x86_64",
        "timestamp": {
          "time": "Tue, 09 Dec 2025 06:33:00 GMT",
          "timesecs": 1765261980
        },
        "connecting_to": {
          "host": "api-int.tenoran.automation.otic.open6g.net",
          "port": 32201
        },
        "cookie": "cmhizw65qeditpqfttlvq3okuewb5m63ybd3",
        "target_bitrate": 70000000,
        "sock_bufsize": 0,
        "sndbuf_actual": 212992,
        "rcvbuf_actual": 212992,
        "test_start": {
          "protocol": "UDP",
          "num_streams": 1,
          "blksize": 1348,
          "omit": 0,
          "duration": 10,
          "bytes": 0,
          "blocks": 0,
          "reverse": 1,
          "tos": 0,
          "target_bitrate": 70000000
        }
      },
      "intervals": [
        {
          "streams": [
            {
              "socket": 5,
              "start": 0,
              "end": 1.000203,
              "seconds": 1.000203013420105,
              "bytes": 8736388,
              "bits_per_second": 69876918.0478807,
              "jitter_ms": 0.2097568825909922,
              "lost_packets": 0,
              "packets": 6481,
              "lost_percent": 0,
              "omitted": false,
              "sender": false
            }
          ],
          "sum": {
            "start": 0,
            "end": 1.000203,
            "seconds": 1.000203013420105,
            "bytes": 8736388,
            "bits_per_second": 69876918.0478807,
            "jitter_ms": 0.2097568825909922,
            "lost_packets": 0,
            "packets": 6481,
            "lost_percent": 0,
            "omitted": false,
            "sender": false
          }
        },
        {
          "streams": [
            {
              "socket": 5,
              "start": 1.000203,
              "end": 2.000208,
              "seconds": 1.0000050067901611,
              "bytes": 8751216,
              "bits_per_second": 70009377.47773765,
              "jitter_ms": 0.2038733977919057,
              "lost_packets": 0,
              "packets": 6492,
              "lost_percent": 0,
              "omitted": false,
              "sender": false
            }
          ],
          "sum": {
            "start": 1.000203,
            "end": 2.000208,
            "seconds": 1.0000050067901611,
            "bytes": 8751216,
            "bits_per_second": 70009377.47773765,
            "jitter_ms": 0.2038733977919057,
            "lost_packets": 0,
            "packets": 6492,
            "lost_percent": 0,
            "omitted": false,
            "sender": false
          }
        },
        {
          "streams": [
            {
              "socket": 5,
              "start": 2.000208,
              "end": 3.000207,
              "seconds": 0.9999989867210388,
              "bytes": 8749868,
              "bits_per_second": 69999014.92852913,
              "jitter_ms": 0.19544858333003912,
              "lost_packets": 0,
              "packets": 6491,
              "lost_percent": 0,
              "omitted": false,
              "sender": false
            }
          ],
          "sum": {
            "start": 2.000208,
            "end": 3.000207,
            "seconds": 0.9999989867210388,
            "bytes": 8749868,
            "bits_per_second": 69999014.92852913,
            "jitter_ms": 0.19544858333003912,
            "lost_packets": 0,
            "packets": 6491,
            "lost_percent": 0,
            "omitted": false,
            "sender": false
          }
        },
        {
          "streams": [
            {
              "socket": 5,
              "start": 3.000207,
              "end": 4.000207,
              "seconds": 1,
              "bytes": 8667640,
              "bits_per_second": 69341120,
              "jitter_ms": 0.18152654125205356,
              "lost_packets": 0,
              "packets": 6430,
              "lost_percent": 0,
              "omitted": false,
              "sender": false
            }
          ],
          "sum": {
            "start": 3.000207,
            "end": 4.000207,
            "seconds": 1,
            "bytes": 8667640,
            "bits_per_second": 69341120,
            "jitter_ms": 0.18152654125205356,
            "lost_packets": 0,
            "packets": 6430,
            "lost_percent": 0,
            "omitted": false,
            "sender": false
          }
        },
        {
          "streams": [
            {
              "socket": 5,
              "start": 4.000207,
              "end": 5.000205,
              "seconds": 0.9999979734420776,
              "bytes": 8832096,
              "bits_per_second": 70656911.19032314,
              "jitter_ms": 0.1934669490537254,
              "lost_packets": 0,
              "packets": 6552,
              "lost_percent": 0,
              "omitted": false,
              "sender": false
            }
          ],
          "sum": {
            "start": 4.000207,
            "end": 5.000205,
            "seconds": 0.9999979734420776,
            "bytes": 8832096,
            "bits_per_second": 70656911.19032314,
            "jitter_ms": 0.1934669490537254,
            "lost_packets": 0,
            "packets": 6552,
            "lost_percent": 0,
            "omitted": false,
            "sender": false
          }
        },
        {
          "streams": [
            {
              "socket": 5,
              "start": 5.000205,
              "end": 6.00021,
              "seconds": 1.0000050067901611,
              "bytes": 8636636,
              "bits_per_second": 69092742.0671388,
              "jitter_ms": 0.38962402614525515,
              "lost_packets": 0,
              "packets": 6407,
              "lost_percent": 0,
              "omitted": false,
              "sender": false
            }
          ],
          "sum": {
            "start": 5.000205,
            "end": 6.00021,
            "seconds": 1.0000050067901611,
            "bytes": 8636636,
            "bits_per_second": 69092742.0671388,
            "jitter_ms": 0.38962402614525515,
            "lost_packets": 0,
            "packets": 6407,
            "lost_percent": 0,
            "omitted": false,
            "sender": false
          }
        },
        {
          "streams": [
            {
              "socket": 5,
              "start": 6.00021,
              "end": 7.000205,
              "seconds": 0.999994993209839,
              "bytes": 8861752,
              "bits_per_second": 70894370.95323896,
              "jitter_ms": 0.22144303448223823,
              "lost_packets": 0,
              "packets": 6574,
              "lost_percent": 0,
              "omitted": false,
              "sender": false
            }
          ],
          "sum": {
            "start": 6.00021,
            "end": 7.000205,
            "seconds": 0.999994993209839,
            "bytes": 8861752,
            "bits_per_second": 70894370.95323896,
            "jitter_ms": 0.22144303448223823,
            "lost_packets": 0,
            "packets": 6574,
            "lost_percent": 0,
            "omitted": false,
            "sender": false
          }
        },
        {
          "streams": [
            {
              "socket": 5,
              "start": 7.000205,
              "end": 8.000205,
              "seconds": 1,
              "bytes": 8623156,
              "bits_per_second": 68985248,
              "jitter_ms": 0.3351707681795658,
              "lost_packets": 0,
              "packets": 6397,
              "lost_percent": 0,
              "omitted": false,
              "sender": false
            }
          ],
          "sum": {
            "start": 7.000205,
            "end": 8.000205,
            "seconds": 1,
            "bytes": 8623156,
            "bits_per_second": 68985248,
            "jitter_ms": 0.3351707681795658,
            "lost_packets": 0,
            "packets": 6397,
            "lost_percent": 0,
            "omitted": false,
            "sender": false
          }
        },
        {
          "streams": [
            {
              "socket": 5,
              "start": 8.000205,
              "end": 9.0002,
              "seconds": 0.999994993209839,
              "bytes": 8876580,
              "bits_per_second": 71012995.5471674,
              "jitter_ms": 0.22026834434806458,
              "lost_packets": 0,
              "packets": 6585,
              "lost_percent": 0,
              "omitted": false,
              "sender": false
            }
          ],
          "sum": {
            "start": 8.000205,
            "end": 9.0002,
            "seconds": 0.999994993209839,
            "bytes": 8876580,
            "bits_per_second": 71012995.5471674,
            "jitter_ms": 0.22026834434806458,
            "lost_packets": 0,
            "packets": 6585,
            "lost_percent": 0,
            "omitted": false,
            "sender": false
          }
        },
        {
          "streams": [
            {
              "socket": 5,
              "start": 9.0002,
              "end": 10.000205,
              "seconds": 1.0000050067901611,
              "bytes": 8658204,
              "bits_per_second": 69265285.20325154,
              "jitter_ms": 0.66955295800441,
              "lost_packets": 0,
              "packets": 6423,
              "lost_percent": 0,
              "omitted": false,
              "sender": false
            }
          ],
          "sum": {
            "start": 9.0002,
            "end": 10.000205,
            "seconds": 1.0000050067901611,
            "bytes": 8658204,
            "bits_per_second": 69265285.20325154,
            "jitter_ms": 0.66955295800441,
            "lost_packets": 0,
            "packets": 6423,
            "lost_percent": 0,
            "omitted": false,
            "sender": false
          }
        }
      ],
      "end": {
        "streams": [
          {
            "udp": {
              "socket": 5,
              "start": 0,
              "end": 10.017654,
              "seconds": 10.017654,
              "bytes": 87649656,
              "bits_per_second": 69996153.5904514,
              "jitter_ms": 0.66955295800441,
              "lost_packets": 0,
              "packets": 65022,
              "lost_percent": 0,
              "out_of_order": 0,
              "sender": false
            }
          }
        ],
        "sum": {
          "start": 0,
          "end": 10.000205,
          "seconds": 10.000205,
          "bytes": 87649656,
          "bits_per_second": 69996153.5904514,
          "jitter_ms": 0.66955295800441,
          "lost_packets": 0,
          "packets": 65022,
          "lost_percent": 0,
          "sender": false
        },
        "sum_sent": {
          "start": 0,
          "end": 10.017654,
          "seconds": 10.017654,
          "bytes": 87649656,
          "bits_per_second": 69996153.5904514,
          "jitter_ms": 0,
          "lost_packets": 0,
          "packets": 65022,
          "lost_percent": 0,
          "sender": true
        },
        "sum_received": {
          "start": 0,
          "end": 10.000205,
          "seconds": 10.000205,
          "bytes": 87393536,
          "bits_per_second": 69913395.5753907,
          "jitter_ms": 0.66955295800441,
          "lost_packets": 0,
          "packets": 64832,
          "lost_percent": 0,
          "sender": false
        },
        "cpu_utilization_percent": {
          "host_total": 9.33613686509617,
          "host_user": 2.69851042558814,
          "host_system": 6.637656288305957,
          "remote_total": 1.7381103233579176,
          "remote_user": 0.134322772551397,
          "remote_system": 1.6037975331766567
        }
      }
    }
  }
}